skill_fallback_llm/LICENSE
skill_fallback_llm/LICENSE.md
skill_fallback_llm/MANIFEST.in
skill_fallback_llm/README.md
skill_fallback_llm/__init__.py
skill_fallback_llm/skill.json
skill_fallback_llm/version.py
skill_fallback_llm/locale/en-us/dialog/end_chat.dialog
skill_fallback_llm/locale/en-us/dialog/fallback_disabled.dialog
skill_fallback_llm/locale/en-us/dialog/fallback_enabled.dialog
skill_fallback_llm/locale/en-us/dialog/no_chat_history.dialog
skill_fallback_llm/locale/en-us/dialog/no_chatgpt.dialog
skill_fallback_llm/locale/en-us/dialog/no_email_address.dialog
skill_fallback_llm/locale/en-us/dialog/notify_llm_active.dialog
skill_fallback_llm/locale/en-us/dialog/sending_chat_history.dialog
skill_fallback_llm/locale/en-us/dialog/start_chat.dialog
skill_fallback_llm/locale/en-us/intent/ask_llm.intent
skill_fallback_llm/locale/en-us/intent/chat_with_llm.intent
skill_fallback_llm/locale/en-us/intent/disable_fallback.intent
skill_fallback_llm/locale/en-us/intent/email_chat_history.intent
skill_fallback_llm/locale/en-us/intent/enable_fallback.intent
skill_fallback_llm/locale/en-us/intent/llm.entity
skill_fallback_llm/locale/en-us/vocab/chat_gpt.voc
skill_fallback_llm/locale/en-us/vocab/exit.voc
skill_fallback_llm/locale/en-us/vocab/fastchat.voc
skill_fallback_llm/locale/uk-ua/dialog/end_chat.dialog
skill_fallback_llm/locale/uk-ua/dialog/fallback_disabled.dialog
skill_fallback_llm/locale/uk-ua/dialog/fallback_enabled.dialog
skill_fallback_llm/locale/uk-ua/dialog/no_chat_history.dialog
skill_fallback_llm/locale/uk-ua/dialog/no_chatgpt.dialog
skill_fallback_llm/locale/uk-ua/dialog/no_email_address.dialog
skill_fallback_llm/locale/uk-ua/dialog/notify_llm_active.dialog
skill_fallback_llm/locale/uk-ua/dialog/sending_chat_history.dialog
skill_fallback_llm/locale/uk-ua/dialog/start_chat.dialog
skill_fallback_llm/locale/uk-ua/intent/ask_llm.intent
skill_fallback_llm/locale/uk-ua/intent/chat_with_llm.intent
skill_fallback_llm/locale/uk-ua/intent/disable_fallback.intent
skill_fallback_llm/neon_skill_fallback_llm.egg-info/PKG-INFO
skill_fallback_llm/neon_skill_fallback_llm.egg-info/SOURCES.txt
skill_fallback_llm/neon_skill_fallback_llm.egg-info/dependency_links.txt
skill_fallback_llm/neon_skill_fallback_llm.egg-info/entry_points.txt
skill_fallback_llm/neon_skill_fallback_llm.egg-info/requires.txt
skill_fallback_llm/neon_skill_fallback_llm.egg-info/top_level.txt
neon_skill_fallback_llm-2.1.0.dist-info/LICENSE
neon_skill_fallback_llm-2.1.0.dist-info/LICENSE.md
neon_skill_fallback_llm-2.1.0.dist-info/METADATA
neon_skill_fallback_llm-2.1.0.dist-info/WHEEL
neon_skill_fallback_llm-2.1.0.dist-info/entry_points.txt
neon_skill_fallback_llm-2.1.0.dist-info/top_level.txt
neon_skill_fallback_llm-2.1.0.dist-info/RECORD
