Metadata-Version: 2.1
Name: neon-skill-fallback-llm
Version: 2.1.0
Home-page: https://github.com/NeonGeckoCom/skill-fallback_llm
Author: Neongecko
Author-email: developers@neon.ai
License: BSD-3-Clause
License-File: LICENSE
License-File: LICENSE.md
Requires-Dist: neon-utils~=1.12
Requires-Dist: ovos-utils>=0.0.28,~=0.0
Requires-Dist: ovos-bus-client>=0.0.3,~=0.0
Requires-Dist: ovos-workshop~=0.1
Requires-Dist: neon-mq-connector~=0.7
Provides-Extra: test
Requires-Dist: neon-minerva[padatious]~=0.3; extra == "test"
